geminiwrapper/__init__.py
geminiwrapper/json_wrapper.py
geminiwrapper/object_wrapper.py
geminiwrapper-0.1.0.dist-info/METADATA
geminiwrapper-0.1.0.dist-info/WHEEL
geminiwrapper-0.1.0.dist-info/top_level.txt
geminiwrapper-0.1.0.dist-info/RECORD
